{
  "name": "Night Purple defaults",
  "include": "./defaults_ui.json",
  "colors": {
    "button.background": "#3d3d3d",
    "extensionButton.prominentBackground": "#3d3d3d",

    "editorCursor.background": "#18141f",
    "editor.selectionForeground": "#18141f",
    "editor.inactiveSelectionBackground": "#18141f",
    "editor.lineHighlightBackground": "#18141f",
    "editor.rangeHighlightForeground": "#18141f",
    "editorBracketMatch.background": "#18141f",
    "editorSuggestWidget.background": "#18141f",
    "editorHoverWidget.background": "#18141f",
    "editorGroup.border": "#18141f",
    "editorOverviewRuler.selectionHighlightForeground": "#3D3D3D",
    "editorWidget.border": "#3D3D3D",
    "editor.selectionBackground": "#2f2b3a",
    "editor.selectionHighlightBackground": "#2f2b3a",
    "editor.hoverHighlightBackground": "#2f2b3a",

    "list.inactiveSelectionBackground": "#1e1c26",
    "list.inactiveSelectionForeground": "#cecece",
    "list.hoverBackground": "#2f2b3a",
    "list.hoverForeground": "#cecece",
    "list.focusBackground": "#2f2b3a",
    "list.focusForeground": "#cecece",
    "list.activeSelectionBackground": "#2e293d",
    "list.dropBackground": "#3D3D3D",

    "activityBar.dropBackground": "#3D3D3D",

    "peekViewEditor.matchHighlightBackground": "#3D3D3D",
    "peekViewResult.matchHighlightBackground": "#3D3D3D",

    "editorOverviewRuler.bracketMatchForeground": "#3D3D3D",
    "editor.background": "#1d1a27",
    "editorWhitespace.foreground": "#1d1a27",
    "editorRuler.foreground": "#1d1a27",
    "editorGutter.background": "#1d1a27",
    "editorGroupHeader.noTabsBackground": "#1d1a27",
    "editorGroupHeader.tabsBackground": "#1d1a27",

    "badge.background": "#1d1a27",

    "sideBarSectionHeader.background": "#1d1a27",
    "activityBar.background": "#1d1a27",

    "tab.activeBackground": "#39334d",
    "tab.inactiveBackground": "#1d1a27",
    "tab.unfocusedActiveBackground": "#2f2b3a",

    "debugExceptionWidget.background": "#1d1a27",

    "peekViewEditor.background": "#1d1a27",

    "panel.background": "#1d1a27",

    "statusBar.background": "#1d1a27",
    "statusBar.debuggingForeground": "#1d1a27",
    "statusBar.noFolderBackground": "#1d1a27",

    "titleBar.activeBackground": "#1d1a27",
    "titleBar.inactiveBackground": "#1d1a27",

    "notifications.background": "#1d1a27",
    "walkThrough.embeddedEditorBackground": "#1c1a27",

    "dropdown.background": "#18141f",

    "input.background": "#18141f",

    "scrollbar.shadow": "#1d1a2790",
    "scrollbarSlider.hoverBackground": "#39334d90",
    "scrollbarSlider.activeBackground": "#2f2b3a90",
    "scrollbarSlider.background": "#39334d60",

    "breadcrumbPicker.background": "#18141f",

    "sideBar.background": "#18141f",

    "activityBar.border": "#18141f",
    "activityBarBadge.background": "#18141f",

    "panel.border": "#18141f",

    "statusBar.border": "#18141f",

    "terminal.background": "#18141f",
    "terminalCursor.background": "#18141f",

    "editorWidget.background": "#1e1c26",
    "editorSuggestWidget.selectedBackground": "#2f2b3a",

    "menubar.selectionBackground": "#39334d",
    "menu.selectionBackground": "#39334d",
    "menu.background": "#1e1c26",

    "peekViewResult.selectionBackground": "#39334d",
    "peekViewTitle.background": "#18141f",
    "peekViewResult.background": "#18141f"
  }
}
